order2.py
order2-0.4.0.dist-info/LICENSE
order2-0.4.0.dist-info/METADATA
order2-0.4.0.dist-info/WHEEL
order2-0.4.0.dist-info/top_level.txt
order2-0.4.0.dist-info/RECORD
